scrapy_model.py
scrapy_model-0.1.5.dist-info/RECORD
scrapy_model-0.1.5.dist-info/DESCRIPTION.rst
scrapy_model-0.1.5.dist-info/top_level.txt
scrapy_model-0.1.5.dist-info/WHEEL
scrapy_model-0.1.5.dist-info/METADATA
scrapy_model-0.1.5.dist-info/metadata.json
