Metadata-Version: 2.0
Name: scrapy-model
Version: 0.1.5
Summary: Scrapy helper to create scrapers from models
Home-page: https://github.com/rochacbruno/scrapy_model
Author: Bruno Rocha
Author-email: rochacbruno@gmail.com
License: BSD
Keywords: scrapy_model
Platform: UNKNOWN
Classifier: Development Status :: 2 - Pre-Alpha
Classifier: Intended Audience :: Developers
Classifier: License :: OSI Approved :: BSD License
Classifier: Natural Language :: English
Classifier: Programming Language :: Python :: 2
Classifier: Programming Language :: Python :: 2.6
Classifier: Programming Language :: Python :: 2.7
Classifier: Programming Language :: Python :: 3
Classifier: Programming Language :: Python :: 3.3
Requires-Dist: wheel (==0.23.0)
Requires-Dist: cffi (==0.8.2)
Requires-Dist: Scrapy (==0.22.2)
Requires-Dist: redis (==2.8.0)
Requires-Dist: requests (==1.2.3)
